mechcalc/__init__.py
mechcalc/__main__.py
mechcalc/main_frame.py
mechcalc/power.py
mechcalc/pump_head.py
mechcalc/pump_power.py
mechcalc/three_phase_power.py
mechcalc/torque.py
mechcalc/vapour_pressure.py
mechcalc/data/motor_power.png
mechcalc/data/my_icon.png
mechcalc/data/power.json
mechcalc/data/power.png
mechcalc/data/pump_head.json
mechcalc/data/pump_head.png
mechcalc/data/pump_power.json
mechcalc/data/pump_power.png
mechcalc/data/three_phase_power.json
mechcalc/data/torque.json
mechcalc/data/torque.png
mechcalc/data/vapour_pressure.json
mechcalc-1.3.3.dist-info/METADATA
mechcalc-1.3.3.dist-info/WHEEL
mechcalc-1.3.3.dist-info/entry_points.txt
mechcalc-1.3.3.dist-info/licenses/LICENSE
mechcalc-1.3.3.dist-info/RECORD
