Metadata-Version: 2.1
Name: mechcalc
Version: 1.3.3
Summary: mechanical engineering calculators
Project-URL: Homepage, https://github.com/ChuckMcKyes/mechcalc-python
Author-email: Chuck McKyes <cemckyes@gmail.com>
License-File: LICENSE
Classifier: License :: OSI Approved :: MIT License
Classifier: Operating System :: OS Independent
Classifier: Programming Language :: Python :: 3
Requires-Python: >=3.9
Requires-Dist: wxpython
